multiconf/__init__.py
multiconf/attribute.py
multiconf/bases.py
multiconf/bits.py
multiconf/check_identifiers.py
multiconf/config_errors.py
multiconf/decorators.py
multiconf/envs.py
multiconf/json_output.py
multiconf/multiconf.py
multiconf/property_wrapper.py
multiconf/repeatable.py
multiconf/thread_state.py
multiconf/typecheck.py
multiconf/values.py
multiconf-10.0.0.dist-info/LICENSE.txt
multiconf-10.0.0.dist-info/METADATA
multiconf-10.0.0.dist-info/WHEEL
multiconf-10.0.0.dist-info/top_level.txt
multiconf-10.0.0.dist-info/zip-safe
multiconf-10.0.0.dist-info/RECORD
