Metadata-Version: 2.1
Name: multiconf
Version: 10.0.0
Summary: Python API providing a set of classes as basis for configuration objects with multiple values per attribute.
Home-page: https://github.com/lhupfeldt/multiconf.git
Author: Lars Hupfeldt Nielsen
Author-email: lhn@hupfeldtit.dk
License: BSD
Classifier: Development Status :: 5 - Production/Stable
Classifier: Environment :: Console
Classifier: Intended Audience :: Developers
Classifier: License :: OSI Approved :: BSD License
Classifier: Natural Language :: English
Classifier: Operating System :: OS Independent
Classifier: Programming Language :: Python :: 3.9
Classifier: Programming Language :: Python :: 3.10
Classifier: Programming Language :: Python :: 3.11
Classifier: Programming Language :: Python :: 3.12
Classifier: Topic :: System :: Installation/Setup
Classifier: Topic :: Software Development :: Testing
Classifier: Topic :: Software Development :: Libraries
Requires-Python: >=3.9
License-File: LICENSE.txt
Requires-Dist: typing-inspect>=0.9.0
Provides-Extra: dev
Requires-Dist: nox; extra == "dev"
